setup.cfg
setup.py
leocornus/__init__.py
leocornus.plonecrypto.egg-info/PKG-INFO
leocornus.plonecrypto.egg-info/SOURCES.txt
leocornus.plonecrypto.egg-info/dependency_links.txt
leocornus.plonecrypto.egg-info/entry_points.txt
leocornus.plonecrypto.egg-info/namespace_packages.txt
leocornus.plonecrypto.egg-info/not-zip-safe
leocornus.plonecrypto.egg-info/requires.txt
leocornus.plonecrypto.egg-info/top_level.txt
leocornus/plonecrypto/HISTORY.txt
leocornus/plonecrypto/LICENSE.GPL
leocornus/plonecrypto/LICENSE.txt
leocornus/plonecrypto/README.txt
leocornus/plonecrypto/__init__.py
leocornus/plonecrypto/configure.zcml
leocornus/plonecrypto/crypto.py
leocornus/plonecrypto/interfaces.py
leocornus/plonecrypto/profiles.zcml
leocornus/plonecrypto/tool.gif
leocornus/plonecrypto/version.txt
leocornus/plonecrypto/crypter/__init__.py
leocornus/plonecrypto/crypter/base.py
leocornus/plonecrypto/crypter/configure.zcml
leocornus/plonecrypto/crypter/czar.pt
leocornus/plonecrypto/crypter/czar.py
leocornus/plonecrypto/profiles/default/toolset.xml
leocornus/plonecrypto/tests/__init__.py
leocornus/plonecrypto/tests/base.py
leocornus/plonecrypto/tests/testCrypto.py