Metadata-Version: 1.0
Name: leocornus.plonecrypto
Version: 0.1
Summary: Plone Cryptographic Toolkit
Home-page: http://plonexp.leocorn.com/xp/leocornus.plonecrypto
Author: Sean Chen
Author-email: sean.chen@leocorn.com
License: GPL
Keywords: Python Plone Zope cryptography
Platform: UNKNOWN
Classifier: Framework :: Zope :: Plone
Classifier: Programming Language :: Python
Classifier: Topic :: Software Development :: Libraries :: Python Modules :: Plone Tool
